[
  {
    "sequence": 1,
    "eventType": "MetadataUpdated",
    "actorUserId": "8289656d-0776-4f88-be92-b2c55504ecba",
    "actorRole": null,
    "fromStatus": null,
    "toStatus": null,
    "field": "metadata.priority,metadata.salesMarketingInput,metadata.opportunityAmount,metadata.comments,metadata.estimatedSubmissionOn",
    "beforeJson": null,
    "afterJson": null,
    "reason": "Initial Workflow V2 metadata save",
    "correlationId": "5bb80598666f4a82bf0954fc81dfc076",
    "occurredAtUtc": "2026-07-19T00:17:51.727345+00:00"
  },
  {
    "sequence": 2,
    "eventType": "MetadataUpdated",
    "actorUserId": "8289656d-0776-4f88-be92-b2c55504ecba",
    "actorRole": null,
    "fromStatus": null,
    "toStatus": null,
    "field": "metadata.priority,metadata.salesMarketingInput,metadata.opportunityAmount,metadata.comments,metadata.estimatedSubmissionOn",
    "beforeJson": null,
    "afterJson": null,
    "reason": "Second Workflow V2 metadata save",
    "correlationId": "09f1808c790d4475847dd3ac267b8fe1",
    "occurredAtUtc": "2026-07-19T00:17:51.97623+00:00"
  },
  {
    "sequence": 3,
    "eventType": "TechnicalReviewStarted",
    "actorUserId": "8289656d-0776-4f88-be92-b2c55504ecba",
    "actorRole": null,
    "fromStatus": "Assembling",
    "toStatus": "UnderTechnicalReview",
    "field": "technical-review",
    "beforeJson": null,
    "afterJson": null,
    "reason": "Required evidence completed by Regulatory Specialist",
    "correlationId": "90f574116733437dbf14f42be4d0daa8",
    "occurredAtUtc": "2026-07-19T00:18:06.148329+00:00"
  },
  {
    "sequence": 4,
    "eventType": "CorrectionRequested",
    "actorUserId": "1f613328-1fae-40e3-8a29-029a8ee3e691",
    "actorRole": null,
    "fromStatus": "UnderTechnicalReview",
    "toStatus": "CorrectionRequested",
    "field": "correction",
    "beforeJson": null,
    "afterJson": null,
    "reason": "Technical evidence needs controlled replacement",
    "correlationId": "7f967e78109d4a698d9461dfa2acd8ea",
    "occurredAtUtc": "2026-07-19T00:18:10.131487+00:00"
  },
  {
    "sequence": 5,
    "eventType": "EvidenceRevisionAdded",
    "actorUserId": "8289656d-0776-4f88-be92-b2c55504ecba",
    "actorRole": null,
    "fromStatus": null,
    "toStatus": null,
    "field": "requirements/70681987-5f0a-4585-b490-c8dc65a3826d/evidence",
    "beforeJson": null,
    "afterJson": null,
    "reason": "Initial scoped correction evidence",
    "correlationId": "9c2d9627deff498cba79de6ac58c1797",
    "occurredAtUtc": "2026-07-19T00:18:14.988401+00:00"
  },
  {
    "sequence": 6,
    "eventType": "EvidenceRevisionAdded",
    "actorUserId": "8289656d-0776-4f88-be92-b2c55504ecba",
    "actorRole": null,
    "fromStatus": null,
    "toStatus": null,
    "field": "requirements/70681987-5f0a-4585-b490-c8dc65a3826d/evidence",
    "beforeJson": null,
    "afterJson": null,
    "reason": "Replacement after reviewer correction request",
    "correlationId": "37304dec5cec42298835d1bdd634aa2b",
    "occurredAtUtc": "2026-07-19T00:18:15.825639+00:00"
  },
  {
    "sequence": 7,
    "eventType": "CorrectionSubmitted",
    "actorUserId": "8289656d-0776-4f88-be92-b2c55504ecba",
    "actorRole": null,
    "fromStatus": "CorrectionRequested",
    "toStatus": "UnderTechnicalReview",
    "field": "correction",
    "beforeJson": null,
    "afterJson": null,
    "reason": "Corrected evidence V2 submitted for technical review",
    "correlationId": "18299781b12a49f88eec0cc20984d591",
    "occurredAtUtc": "2026-07-19T00:18:16.620154+00:00"
  },
  {
    "sequence": 8,
    "eventType": "TechnicalReviewCompleted",
    "actorUserId": "1f613328-1fae-40e3-8a29-029a8ee3e691",
    "actorRole": null,
    "fromStatus": "UnderTechnicalReview",
    "toStatus": "ReadyForSubmission",
    "field": "technical-review",
    "beforeJson": null,
    "afterJson": null,
    "reason": "Reviewer completed corrected technical review",
    "correlationId": "6d6163341a394df2a1c973e02e898b8e",
    "occurredAtUtc": "2026-07-19T00:18:25.732749+00:00"
  }
]